{"id":"Gangplank","position":["TOP"],"TOP":{"spell":["SummonerFlash","SummonerTeleport","SummonerFlash","SummonerDot"],"skill":{"masterOrder":[{"order":"QEW","pickRate":"99.65%","winRate":"56.65%"}],"first3Order":[{"order":"QEW","pickRate":"73.97%"},{"order":"QEQ","pickRate":"16.97%"},{"order":"QWE","pickRate":"4.41%"},{"order":"EQW","pickRate":"0.73%"}]},"rune":[{"summary":{"mainRune":"8437","subRune":"8300","pickRate":"57.53%","winRate":"48.52%"},"detail":[{"main":["8437","8446","8473","8451"],"sub":["8345","8352"],"chip":["5008","5008","5002"],"pickRate":"27.85%","winRate":"47.24%"},{"main":["8437","8446","8473","8451"],"sub":["8345","8352"],"chip":["5008","5008","5003"],"pickRate":"6.20%","winRate":"53.31%"},{"main":["8437","8446","8473","8453"],"sub":["8345","8352"],"chip":["5008","5008","5002"],"pickRate":"3.35%","winRate":"50.92%"},{"main":["8437","8446","8444","8451"],"sub":["8345","8352"],"chip":["5008","5008","5002"],"pickRate":"3.08%","winRate":"47.33%"},{"main":["8437","8446","8444","8451"],"sub":["8345","8352"],"chip":["5008","5008","5003"],"pickRate":"2.63%","winRate":"42.19%"}]},{"summary":{"mainRune":"8369","subRune":"8400","pickRate":"25.02%","winRate":"50.94%"},"detail":[{"main":["8369","8304","8345","8352"],"sub":["8473","8451"],"chip":["5008","5008","5002"],"pickRate":"7.49%","winRate":"50.96%"},{"main":["8369","8304","8345","8352"],"sub":["8446","8473"],"chip":["5008","5008","5002"],"pickRate":"2.11%","winRate":"46.60%"},{"main":["8369","8304","8345","8352"],"sub":["8473","8451"],"chip":["5008","5008","5003"],"pickRate":"1.95%","winRate":"60.00%"},{"main":["8369","8304","8321","8352"],"sub":["8473","8451"],"chip":["5008","5008","5002"],"pickRate":"1.60%","winRate":"46.15%"},{"main":["8369","8304","8345","8352"],"sub":["8473","8453"],"chip":["5008","5008","5002"],"pickRate":"0.84%","winRate":"46.34%"}]},{"summary":{"mainRune":"8369","subRune":"8100","pickRate":"4.58%","winRate":"47.98%"},"detail":[{"main":["8369","8304","8345","8352"],"sub":["8139","8106"],"chip":["5008","5008","5002"],"pickRate":"1.38%","winRate":"52.24%"},{"main":["8369","8304","8321","8352"],"sub":["8139","8106"],"chip":["5008","5008","5002"],"pickRate":"0.43%","winRate":"52.38%"},{"main":["8369","8304","8345","8352"],"sub":["8139","8106"],"chip":["5008","5008","5003"],"pickRate":"0.39%","winRate":"63.16%"},{"main":["8369","8304","8345","8352"],"sub":["8139","8135"],"chip":["5008","5008","5002"],"pickRate":"0.33%","winRate":"50.00%"},{"main":["8369","8304","8321","8352"],"sub":["8139","8106"],"chip":["5008","5008","5003"],"pickRate":"0.18%","winRate":"66.67%"}]},{"summary":{"mainRune":"8369","subRune":"8200","pickRate":"4.11%","winRate":"48.50%"},"detail":[{"main":["8369","8304","8345","8352"],"sub":["8226","8210"],"chip":["5008","5008","5002"],"pickRate":"0.41%","winRate":"65.00%"},{"main":["8369","8304","8345","8352"],"sub":["8226","8210"],"chip":["5008","5008","5003"],"pickRate":"0.27%","winRate":"53.85%"},{"main":["8369","8304","8345","8352"],"sub":["8210","8237"],"chip":["5008","5008","5002"],"pickRate":"0.27%","winRate":"46.15%"},{"main":["8369","8304","8345","8352"],"sub":["8226","8237"],"chip":["5008","5008","5002"],"pickRate":"0.18%","winRate":"44.44%"},{"main":["8369","8304","8345","8347"],"sub":["8226","8210"],"chip":["5008","5008","5002"],"pickRate":"0.14%","winRate":"28.57%"}]},{"summary":{"mainRune":"8437","subRune":"8200","pickRate":"2.98%","winRate":"54.48%"},"detail":[{"main":["8437","8446","8473","8451"],"sub":["8275","8237"],"chip":["5008","5008","5002"],"pickRate":"0.39%","winRate":"68.42%"},{"main":["8437","8446","8473","8451"],"sub":["8210","8237"],"chip":["5005","5008","5002"],"pickRate":"0.31%","winRate":"60.00%"},{"main":["8437","8446","8473","8451"],"sub":["8210","8237"],"chip":["5008","5008","5002"],"pickRate":"0.21%","winRate":"30.00%"},{"main":["8437","8446","8473","8453"],"sub":["8275","8237"],"chip":["5008","5008","5002"],"pickRate":"0.12%","winRate":"33.33%"},{"main":["8437","8446","8444","8451"],"sub":["8210","8237"],"chip":["5008","5008","5002"],"pickRate":"0.08%","winRate":"50.00%"}]}],"item":{"coreItems":[{"items":["3078","3033","6676"],"winRate":"53.47%","pickRate":"10.52%"},{"items":["3078","6676","3033"],"winRate":"52.04%","pickRate":"10.21%"},{"items":["3078","3053","3033"],"winRate":"56.89%","pickRate":"5.80%"},{"items":["3508","6673","3031"],"winRate":"59.49%","pickRate":"5.49%"},{"items":["3508","6673","6676"],"winRate":"49.30%","pickRate":"4.93%"},{"items":["3078","6676","3053"],"winRate":"56.20%","pickRate":"4.76%"},{"items":["3078","3053","6676"],"winRate":"57.14%","pickRate":"4.13%"},{"items":["3078","6676","3036"],"winRate":"50.00%","pickRate":"3.96%"}],"startItems":[{"items":["2033"],"winRate":"49.45%","pickRate":"94.46%"},{"items":["3070","2003","2003"],"winRate":"40.00%","pickRate":"2.54%"},{"items":["2033","3364"],"winRate":"42.42%","pickRate":"0.70%"},{"items":["2033","2031"],"winRate":"60.87%","pickRate":"0.49%"},{"items":["1054","2003"],"winRate":"52.94%","pickRate":"0.36%"}],"shoes":[{"item":"3158","pickRate":"51.21%","winRate":"50.68%"},{"item":"3047","pickRate":"39.16%","winRate":"49.67%"},{"item":"3111","pickRate":"8.46%","winRate":"52.05%"}]}}}