{"id":"RekSai","position":["JUNGLE"],"JUNGLE":{"spell":["SummonerFlash","SummonerSmite","SummonerSmite","SummonerDot"],"skill":{"masterOrder":[{"order":"QEW","pickRate":"74.50%","winRate":"64.67%"},{"order":"EQW","pickRate":"24.36%","winRate":"69.29%"},{"order":"QWE","pickRate":"1.14%","winRate":"68.00%"}],"first3Order":[{"order":"QWE","pickRate":"88.14%"},{"order":"QEW","pickRate":"1.69%"}]},"rune":[{"summary":{"mainRune":"8010","subRune":"8200","pickRate":"43.19%","winRate":"51.68%"},"detail":[{"main":["8010","9111","9104","8014"],"sub":["8275","8232"],"chip":["5005","5008","5002"],"pickRate":"32.13%","winRate":"52.18%"},{"main":["8010","9111","9104","8014"],"sub":["8275","8232"],"chip":["5005","5008","5003"],"pickRate":"2.73%","winRate":"54.55%"},{"main":["8010","9111","9104","8014"],"sub":["8275","8233"],"chip":["5005","5008","5002"],"pickRate":"2.55%","winRate":"46.53%"},{"main":["8010","9111","9105","8014"],"sub":["8275","8232"],"chip":["5005","5008","5002"],"pickRate":"1.72%","winRate":"52.58%"},{"main":["8010","9111","9104","8014"],"sub":["8275","8234"],"chip":["5005","5008","5002"],"pickRate":"0.48%","winRate":"44.44%"}]},{"summary":{"mainRune":"8010","subRune":"8300","pickRate":"27.05%","winRate":"54.97%"},"detail":[{"main":["8010","9111","9104","8014"],"sub":["8304","8347"],"chip":["5005","5008","5002"],"pickRate":"17.28%","winRate":"55.43%"},{"main":["8010","9111","9105","8014"],"sub":["8304","8347"],"chip":["5005","5008","5002"],"pickRate":"2.81%","winRate":"50.94%"},{"main":["8010","9111","9104","8014"],"sub":["8304","8347"],"chip":["5005","5008","5003"],"pickRate":"2.62%","winRate":"56.08%"},{"main":["8010","9111","9104","8014"],"sub":["8321","8347"],"chip":["5005","5008","5002"],"pickRate":"1.17%","winRate":"48.48%"},{"main":["8010","9111","9104","8014"],"sub":["8304","8410"],"chip":["5005","5008","5002"],"pickRate":"1.04%","winRate":"57.63%"}]},{"summary":{"mainRune":"9923","subRune":"8000","pickRate":"6.30%","winRate":"55.06%"},"detail":[{"main":["9923","8126","8138","8105"],"sub":["9111","9104"],"chip":["5005","5008","5002"],"pickRate":"1.93%","winRate":"54.13%"},{"main":["9923","8126","8138","8135"],"sub":["9111","9104"],"chip":["5005","5008","5002"],"pickRate":"0.76%","winRate":"55.81%"},{"main":["9923","8126","8138","8134"],"sub":["9111","9104"],"chip":["5005","5008","5002"],"pickRate":"0.57%","winRate":"56.25%"},{"main":["9923","8126","8138","8105"],"sub":["9111","8014"],"chip":["5005","5008","5002"],"pickRate":"0.30%","winRate":"64.71%"},{"main":["9923","8126","8136","8105"],"sub":["9111","9104"],"chip":["5005","5008","5002"],"pickRate":"0.27%","winRate":"60.00%"}]},{"summary":{"mainRune":"8010","subRune":"8100","pickRate":"5.51%","winRate":"54.34%"},"detail":[{"main":["8010","9111","9104","8014"],"sub":["8126","8134"],"chip":["5005","5008","5002"],"pickRate":"1.38%","winRate":"50.00%"},{"main":["8010","9111","9104","8014"],"sub":["8138","8134"],"chip":["5005","5008","5002"],"pickRate":"0.97%","winRate":"54.55%"},{"main":["8010","9111","9104","8014"],"sub":["8126","8105"],"chip":["5005","5008","5002"],"pickRate":"0.69%","winRate":"53.85%"},{"main":["8010","9111","9104","8014"],"sub":["8138","8134"],"chip":["5008","5008","5002"],"pickRate":"0.30%","winRate":"82.35%"},{"main":["8010","9111","9104","8014"],"sub":["8143","8105"],"chip":["5005","5008","5002"],"pickRate":"0.23%","winRate":"53.85%"}]},{"summary":{"mainRune":"8124","subRune":"8000","pickRate":"5.05%","winRate":"56.14%"},"detail":[{"main":["8124","8126","8138","8134"],"sub":["9111","9104"],"chip":["5005","5008","5002"],"pickRate":"2.43%","winRate":"52.55%"},{"main":["8124","8126","8136","8134"],"sub":["9111","9104"],"chip":["5005","5008","5002"],"pickRate":"0.81%","winRate":"67.39%"},{"main":["8124","8126","8138","8134"],"sub":["9111","9104"],"chip":["5005","5008","5003"],"pickRate":"0.30%","winRate":"64.71%"},{"main":["8124","8126","8138","8134"],"sub":["9111","8014"],"chip":["5005","5008","5002"],"pickRate":"0.25%","winRate":"71.43%"},{"main":["8124","8126","8138","8105"],"sub":["9111","9104"],"chip":["5005","5008","5002"],"pickRate":"0.21%","winRate":"66.67%"}]}],"item":{"coreItems":[{"items":["6693","3814","3053"],"winRate":"60.68%","pickRate":"29.73%"},{"items":["6693","3814","3026"],"winRate":"65.47%","pickRate":"16.14%"},{"items":["6693","3053","3026"],"winRate":"58.23%","pickRate":"9.64%"},{"items":["6693","3814","3071"],"winRate":"52.83%","pickRate":"4.10%"},{"items":["6693","3053","3814"],"winRate":"55.88%","pickRate":"3.95%"},{"items":["6693","3814","6695"],"winRate":"56.45%","pickRate":"2.40%"},{"items":["6693","3071","3053"],"winRate":"54.00%","pickRate":"1.94%"},{"items":["6693","3053","3071"],"winRate":"58.97%","pickRate":"1.51%"}],"startItems":[{"items":["1039","2031"],"winRate":"53.34%","pickRate":"53.18%"},{"items":["1039","2031","3364"],"winRate":"56.48%","pickRate":"27.27%"},{"items":["1035","2031"],"winRate":"50.25%","pickRate":"10.83%"},{"items":["1035","2031","3364"],"winRate":"47.94%","pickRate":"4.79%"},{"items":["1039","2031","3364","3364"],"winRate":"60.53%","pickRate":"0.68%"}],"shoes":[{"item":"3047","pickRate":"61.85%","winRate":"53.74%"},{"item":"3111","pickRate":"28.00%","winRate":"56.28%"},{"item":"3006","pickRate":"7.37%","winRate":"59.58%"}]}}}